LICENSE.txt
MANIFEST.in
README.rst
run_tests.py
setup.py
bendcode/__init__.py
bendcode/bendcode.py
bendcode/exceptions.py
bendcode/tests.py
bendcode.egg-info/PKG-INFO
bendcode.egg-info/SOURCES.txt
bendcode.egg-info/dependency_links.txt
bendcode.egg-info/top_level.txt