Metadata-Version: 1.1
Name: bendcode
Version: 1.0.0
Summary: Python module to decode Bencoded data
Home-page: https://github.com/sanketh95/BenDcode
Author: Sanketh Mopuru
Author-email: sanketh.mopuru@gmail.com
License: GPLv2
Keywords: bencoding,bittorrent
Platform: UNKNOWN
Classifier: Development Status :: 5 - Production/Stable
Classifier: Intended Audience :: Developers
Classifier: License :: OSI Approved :: GNU General Public License v2 (GPLv2)
Classifier: Programming Language :: Python :: 2
Classifier: Programming Language :: Python :: 2.6
Classifier: Programming Language :: Python :: 2.7
